[
  { "name": "承德避暑山庄及周围寺庙景区", "coords": [117.9270, 40.9936] },
  { "name": "安新白洋淀景区", "coords": [115.9631, 38.9418] },
  { "name": "野三坡风景区", "coords": [115.3794, 39.6670] },
  { "name": "清西陵景区", "coords": [115.3420, 39.3597] },
  { "name": "白石山国家地质公园", "coords": [114.6986, 39.2094] },
  { "name": "西柏坡景区", "coords": [113.9313, 38.3410] },
  { "name": "天桂山风景名胜区", "coords": [113.7364, 38.2554] },
  { "name": "清东陵景区", "coords": [117.6759, 40.1679] },
  { "name": "娲皇宫景区", "coords": [113.6223, 36.6336] },
  { "name": "广府古城景区", "coords": [114.7242, 36.7004] },
  { "name": "山海关景区", "coords": [119.7925, 39.9681] },
  { "name": "崇礼冰雪旅游区", "coords": [115.2838, 40.9733] }
]